{
  "replace": false,
  "order": 0,
  "enabled": true,
  "origins": [
    "origins:form_original_before_enable",
    "origins:form_original_shifter",
    "origins:form_bat_2",
    "origins:form_bat_1",
    "origins:form_bat_0",
    "origins:form_axolotl_0",
    "origins:form_axolotl_1",
    "origins:form_axolotl_2",
    "origins:form_ocelot_0",
    "origins:form_ocelot_1",
    "origins:form_ocelot_2",
    "origins:form_ocelot_3",
    "origins:form_familiar_fox_0",
    "origins:form_familiar_fox_1",
    "origins:form_familiar_fox_2",
    "origins:form_familiar_fox_3",
    "origins:form_snow_fox_0",
    "origins:form_snow_fox_1",
    "origins:form_snow_fox_2",
    "origins:form_snow_fox_3",
    "origins:form_allay_sp",
    "origins:form_feral_cat_sp",
    "origins:form_alpha_0",
    "origins:form_alpha_1",
    "origins:form_alpha_2",
    "origins:form_beta_0",
    "origins:form_beta_1",
    "origins:form_beta_2",
    "origins:form_gamma_0",
    "origins:form_gamma_1",
    "origins:form_gamma_2",
    "origins:form_omega_sp",
    "origins:form_psi_sp",
    "origins:form_chi_sp",
    "origins:form_phi_sp"
  ],
  "allow_random": true,
  "exclude_random": [
  ],
  "allow_random_unchoosable": false,
  "hidden": false
}